{
  "symbol": "XLE",
  "aliases": [],
  "asof_td_label": "2025-12-24",
  "asof_td_index": 37,
  "asof_tw_index": 7,
  "cycle_specs": {
    "DAILY": {
      "version": 1,
      "length": 26,
      "anchor": "2025-12-31"
    },
    "WEEKLY": {
      "version": 1,
      "length": 29,
      "anchor": "2026-05-03"
    }
  },
  "cycle_proximity": {
    "DAILY": {
      "status": "NONE"
    },
    "WEEKLY": {
      "status": "NONE",
      "prewindow_start": "2026-03-06",
      "prewindow_end": "2026-03-13",
      "core_start": "2026-03-20",
      "core_end": "2026-05-01",
      "median": "2026-05-08",
      "weeks_to_core_start": 12
    }
  },
  "overlap": {},
  "notes": [
    {
      "author": "Bernard",
      "note_type": "LEVELS",
      "scope": "BOTH",
      "price_reference": "OTHER",
      "bullets": [
        "Bounce permission: reclaim + hold above ~44.8\u201345.2 (back above the broken micro-shelf / next pendulum lane)",
        "Failure trigger: acceptance below ~43.6\u201343.8 \u2192 daily trough fails, next leg down opens"
      ],
      "asof": "2025-12-22"
    }
  ],
  "astro": {
    "next_primary": null,
    "backup_events": []
  }
}